{
  "content": [
    {
      "type": "title",
      "text": "第5話　捕まった陽奈"
    },
    {
      "type": "text",
      "text": "蛇族兵A:",
      "start": null,
      "end": null,
      "annotation": ""
    },
    {
      "type": "text",
      "text": " ",
      "start": null,
      "end": null,
      "annotation": ""
    },
    {
      "type": "text",
      "text": "报告",
      "start": 3.393356,
      "end": 3.860026,
      "annotation": "Bàogào"
    },
    {
      "type": "text",
      "text": "|",
      "start": null,
      "end": null,
      "annotation": ""
    },
    {
      "type": "text",
      "text": "船长",
      "start": 3.860026,
      "end": 4.606698,
      "annotation": "chuánzhǎng"
    },
    {
      "type": "text",
      "text": "! ",
      "start": null,
      "end": null,
      "annotation": ""
    },
    {
      "type": "text",
      "text": "前方",
      "start": 4.606698,
      "end": 5.160146,
      "annotation": "Qiánfāng"
    },
    {
      "type": "text",
      "text": "|",
      "start": null,
      "end": null,
      "annotation": ""
    },
    {
      "type": "text",
      "text": "有不明",
      "start": 5.160146,
      "end": 5.67016,
      "annotation": "yǒu bù míng"
    },
    {
      "type": "text",
      "text": "|",
      "start": null,
      "end": null,
      "annotation": ""
    },
    {
      "type": "text",
      "text": "飞船",
      "start": 5.67016,
      "end": 6.304043,
      "annotation": "fēichuán"
    },
    {
      "type": "text",
      "text": ".\n",
      "start": null,
      "end": null,
      "annotation": ""
    },
    {
      "type": "text",
      "text": "蛇族船长:",
      "start": null,
      "end": null,
      "annotation": ""
    },
    {
      "type": "text",
      "text": " ",
      "start": null,
      "end": null,
      "annotation": ""
    },
    {
      "type": "text",
      "text": "去",
      "start": 7.140049,
      "end": 8.080056,
      "annotation": "Qù"
    },
    {
      "type": "text",
      "text": "|",
      "start": null,
      "end": null,
      "annotation": ""
    },
    {
      "type": "text",
      "text": "查查",
      "start": 8.080056,
      "end": 8.853394,
      "annotation": "chácha"
    },
    {
      "type": "text",
      "text": "|",
      "start": null,
      "end": null,
      "annotation": ""
    },
    {
      "type": "text",
      "text": "看",
      "start": 8.853394,
      "end": 9.688557,
      "annotation": "kàn"
    },
    {
      "type": "text",
      "text": ".\n",
      "start": null,
      "end": null,
      "annotation": ""
    },
    {
      "type": "text",
      "text": "蛇族兵AB:",
      "start": null,
      "end": null,
      "annotation": ""
    },
    {
      "type": "text",
      "text": " ",
      "start": null,
      "end": null,
      "annotation": ""
    },
    {
      "type": "text",
      "text": "是",
      "start": 9.765401,
      "end": 10.92679,
      "annotation": "Shì"
    },
    {
      "type": "text",
      "text": "!\n",
      "start": null,
      "end": null,
      "annotation": ""
    },
    {
      "type": "text",
      "text": "蛇族兵B:",
      "start": null,
      "end": null,
      "annotation": ""
    },
    {
      "type": "text",
      "text": " ",
      "start": null,
      "end": null,
      "annotation": ""
    },
    {
      "type": "text",
      "text": "喂",
      "start": 13.140091,
      "end": 14.119522,
      "annotation": "Wèi"
    },
    {
      "type": "text",
      "text": ", ",
      "start": null,
      "end": null,
      "annotation": ""
    },
    {
      "type": "text",
      "text": "你看",
      "start": 14.119522,
      "end": 15.009437,
      "annotation": "nǐ kàn"
    },
    {
      "type": "text",
      "text": ", ",
      "start": null,
      "end": null,
      "annotation": ""
    },
    {
      "type": "text",
      "text": "那是",
      "start": 15.009437,
      "end": 15.313439,
      "annotation": "nà shì"
    },
    {
      "type": "text",
      "text": "|",
      "start": null,
      "end": null,
      "annotation": ""
    },
    {
      "type": "text",
      "text": "什么",
      "start": 15.313439,
      "end": 15.954618,
      "annotation": "shénme"
    },
    {
      "type": "text",
      "text": "?\n",
      "start": null,
      "end": null,
      "annotation": ""
    },
    {
      "type": "text",
      "text": "阳奈:",
      "start": null,
      "end": null,
      "annotation": ""
    },
    {
      "type": "text",
      "text": " ",
      "start": null,
      "end": null,
      "annotation": ""
    },
    {
      "type": "text",
      "text": "呼",
      "start": 17.993458,
      "end": 21.282989,
      "annotation": "Hū"
    },
    {
      "type": "text",
      "text": "------ ",
      "start": null,
      "end": null,
      "annotation": ""
    },
    {
      "type": "text",
      "text": "呼",
      "start": 21.282989,
      "end": 23.266399,
      "annotation": "hū"
    },
    {
      "type": "text",
      "text": "------\n",
      "start": null,
      "end": null,
      "annotation": ""
    },
    {
      "type": "text",
      "text": "蛇族兵A:",
      "start": null,
      "end": null,
      "annotation": ""
    },
    {
      "type": "text",
      "text": " ",
      "start": null,
      "end": null,
      "annotation": ""
    },
    {
      "type": "text",
      "text": "八成",
      "start": 23.365496,
      "end": 23.940166,
      "annotation": "Bāchéng"
    },
    {
      "type": "text",
      "text": "|",
      "start": null,
      "end": null,
      "annotation": ""
    },
    {
      "type": "text",
      "text": "是在",
      "start": 23.940166,
      "end": 24.186834,
      "annotation": "shì zài"
    },
    {
      "type": "text",
      "text": "|",
      "start": null,
      "end": null,
      "annotation": ""
    },
    {
      "type": "text",
      "text": "睡觉",
      "start": 24.186834,
      "end": 24.830211,
      "annotation": "shuìjiào"
    },
    {
      "type": "text",
      "text": ". ",
      "start": null,
      "end": null,
      "annotation": ""
    },
    {
      "type": "text",
      "text": "用你的",
      "start": 24.830211,
      "end": 25.47351,
      "annotation": "Yòng nǐ de"
    },
    {
      "type": "text",
      "text": "|",
      "start": null,
      "end": null,
      "annotation": ""
    },
    {
      "type": "text",
      "text": "尾巴",
      "start": 25.47351,
      "end": 25.846846,
      "annotation": "wěiba"
    },
    {
      "type": "text",
      "text": "|",
      "start": null,
      "end": null,
      "annotation": ""
    },
    {
      "type": "text",
      "text": "捅捅看",
      "start": 25.846846,
      "end": 26.689899,
      "annotation": "tǒngtong kàn"
    },
    {
      "type": "text",
      "text": ".\n",
      "start": null,
      "end": null,
      "annotation": ""
    },
    {
      "type": "text",
      "text": "阳奈:",
      "start": null,
      "end": null,
      "annotation": ""
    },
    {
      "type": "text",
      "text": " ",
      "start": null,
      "end": null,
      "annotation": ""
    },
    {
      "type": "text",
      "text": "啊",
      "start": 26.941704,
      "end": 27.373523,
      "annotation": "Ā"
    },
    {
      "type": "text",
      "text": "!\n",
      "start": null,
      "end": null,
      "annotation": ""
    },
    {
      "type": "text",
      "text": "蛇族兵AB:",
      "start": null,
      "end": null,
      "annotation": ""
    },
    {
      "type": "text",
      "text": " ",
      "start": null,
      "end": null,
      "annotation": ""
    },
    {
      "type": "text",
      "text": "哇",
      "start": 27.373523,
      "end": 28.448201,
      "annotation": "Wā"
    },
    {
      "type": "text",
      "text": "!\n",
      "start": null,
      "end": null,
      "annotation": ""
    },
    {
      "type": "text",
      "text": "阳奈:",
      "start": null,
      "end": null,
      "annotation": ""
    },
    {
      "type": "text",
      "text": " ",
      "start": null,
      "end": null,
      "annotation": ""
    },
    {
      "type": "text",
      "text": "啊",
      "start": 28.680199,
      "end": 29.632266,
      "annotation": "Ā"
    },
    {
      "type": "text",
      "text": "! ",
      "start": null,
      "end": null,
      "annotation": ""
    },
    {
      "type": "text",
      "text": "你们",
      "start": 29.632266,
      "end": 30.246877,
      "annotation": "Nǐmen"
    },
    {
      "type": "text",
      "text": "|",
      "start": null,
      "end": null,
      "annotation": ""
    },
    {
      "type": "text",
      "text": "是谁啊",
      "start": 30.246877,
      "end": 31.251429,
      "annotation": "shì shéi a"
    },
    {
      "type": "text",
      "text": "?!\n",
      "start": null,
      "end": null,
      "annotation": ""
    },
    {
      "type": "text",
      "text": "蛇族兵B:",
      "start": null,
      "end": null,
      "annotation": ""
    },
    {
      "type": "text",
      "text": " ",
      "start": null,
      "end": null,
      "annotation": ""
    },
    {
      "type": "text",
      "text": "我们是",
      "start": 31.783182,
      "end": 33.060229,
      "annotation": "Wǒmen shì"
    },
    {
      "type": "text",
      "text": "|",
      "start": null,
      "end": null,
      "annotation": ""
    },
    {
      "type": "text",
      "text": "蛇族",
      "start": 33.060229,
      "end": 33.833568,
      "annotation": "Shézú"
    },
    {
      "type": "text",
      "text": ".\n",
      "start": null,
      "end": null,
      "annotation": ""
    },
    {
      "type": "text",
      "text": "阳奈:",
      "start": null,
      "end": null,
      "annotation": ""
    },
    {
      "type": "text",
      "text": " ",
      "start": null,
      "end": null,
      "annotation": ""
    },
    {
      "type": "text",
      "text": "蛇",
      "start": 33.833568,
      "end": 35.296606,
      "annotation": "Shé"
    },
    {
      "type": "text",
      "text": "...... ",
      "start": null,
      "end": null,
      "annotation": ""
    },
    {
      "type": "text",
      "text": "说",
      "start": 35.296606,
      "end": 36.032249,
      "annotation": "shuō"
    },
    {
      "type": "text",
      "text": "...... ",
      "start": null,
      "end": null,
      "annotation": ""
    },
    {
      "type": "text",
      "text": "说话了",
      "start": 36.032249,
      "end": 37.689513,
      "annotation": "shuōhuà le"
    },
    {
      "type": "text",
      "text": "?!\n",
      "start": null,
      "end": null,
      "annotation": ""
    },
    {
      "type": "text",
      "text": "蛇族兵A:",
      "start": null,
      "end": null,
      "annotation": ""
    },
    {
      "type": "text",
      "text": " ",
      "start": null,
      "end": null,
      "annotation": ""
    },
    {
      "type": "text",
      "text": "你是",
      "start": 37.689513,
      "end": 38.493601,
      "annotation": "Nǐ shì"
    },
    {
      "type": "text",
      "text": "|",
      "start": null,
      "end": null,
      "annotation": ""
    },
    {
      "type": "text",
      "text": "什么",
      "start": 38.493601,
      "end": 38.786936,
      "annotation": "shénme"
    },
    {
      "type": "text",
      "text": "|",
      "start": null,
      "end": null,
      "annotation": ""
    },
    {
      "type": "text",
      "text": "东西",
      "start": 38.786936,
      "end": 39.760024,
      "annotation": "dōngxi"
    },
    {
      "type": "text",
      "text": "?\n",
      "start": null,
      "end": null,
      "annotation": ""
    },
    {
      "type": "text",
      "text": "阳奈:",
      "start": null,
      "end": null,
      "annotation": ""
    },
    {
      "type": "text",
      "text": " ",
      "start": null,
      "end": null,
      "annotation": ""
    },
    {
      "type": "text",
      "text": "什么",
      "start": 39.760024,
      "end": 40.480281,
      "annotation": "Shénme"
    },
    {
      "type": "text",
      "text": "|",
      "start": null,
      "end": null,
      "annotation": ""
    },
    {
      "type": "text",
      "text": "东西",
      "start": 40.480281,
      "end": 41.427996,
      "annotation": "dōngxi"
    },
    {
      "type": "text",
      "text": "? ",
      "start": null,
      "end": null,
      "annotation": ""
    },
    {
      "type": "text",
      "text": "我",
      "start": 41.427996,
      "end": 41.82029,
      "annotation": "Wǒ"
    },
    {
      "type": "text",
      "text": "|",
      "start": null,
      "end": null,
      "annotation": ""
    },
    {
      "type": "text",
      "text": "当然",
      "start": 41.82029,
      "end": 42.16696,
      "annotation": "dāngrán"
    },
    {
      "type": "text",
      "text": "|",
      "start": null,
      "end": null,
      "annotation": ""
    },
    {
      "type": "text",
      "text": "是人",
      "start": 42.16696,
      "end": 42.686963,
      "annotation": "shì rén"
    },
    {
      "type": "text",
      "text": "|",
      "start": null,
      "end": null,
      "annotation": ""
    },
    {
      "type": "text",
      "text": "啦",
      "start": 42.686963,
      "end": 43.485261,
      "annotation": "la"
    },
    {
      "type": "text",
      "text": "! ",
      "start": null,
      "end": null,
      "annotation": ""
    },
    {
      "type": "text",
      "text": "我",
      "start": 43.485261,
      "end": 44.333733,
      "annotation": "Wǒ"
    },
    {
      "type": "text",
      "text": ", ",
      "start": null,
      "end": null,
      "annotation": ""
    },
    {
      "type": "text",
      "text": "高中",
      "start": 44.333733,
      "end": 45.001276,
      "annotation": "gāozhōng"
    },
    {
      "type": "text",
      "text": "|",
      "start": null,
      "end": null,
      "annotation": ""
    },
    {
      "type": "text",
      "text": "女生",
      "start": 45.001276,
      "end": 45.851365,
      "annotation": "nǚshēng"
    },
    {
      "type": "text",
      "text": "!\n",
      "start": null,
      "end": null,
      "annotation": ""
    },
    {
      "type": "text",
      "text": "蛇族船长:",
      "start": null,
      "end": null,
      "annotation": ""
    },
    {
      "type": "text",
      "text": " ",
      "start": null,
      "end": null,
      "annotation": ""
    },
    {
      "type": "text",
      "text": "从没",
      "start": 47.112326,
      "end": 48.013667,
      "annotation": "Cóng méi"
    },
    {
      "type": "text",
      "text": "|",
      "start": null,
      "end": null,
      "annotation": ""
    },
    {
      "type": "text",
      "text": "见过",
      "start": 48.013667,
      "end": 48.725775,
      "annotation": "jiànguo"
    },
    {
      "type": "text",
      "text": "|",
      "start": null,
      "end": null,
      "annotation": ""
    },
    {
      "type": "text",
      "text": "这种",
      "start": 48.725775,
      "end": 49.493677,
      "annotation": "zhè zhǒng"
    },
    {
      "type": "text",
      "text": "|",
      "start": null,
      "end": null,
      "annotation": ""
    },
    {
      "type": "text",
      "text": "生物",
      "start": 49.493677,
      "end": 50.696486,
      "annotation": "shēngwù"
    },
    {
      "type": "text",
      "text": ".\n",
      "start": null,
      "end": null,
      "annotation": ""
    },
    {
      "type": "spacer",
      "text": "蛇族船长:",
      "start": null,
      "end": null,
      "annotation": ""
    },
    {
      "type": "text",
      "text": " ",
      "start": null,
      "end": null,
      "annotation": ""
    },
    {
      "type": "text",
      "text": "你是",
      "start": 50.865685,
      "end": 52.180363,
      "annotation": "Nǐ shì"
    },
    {
      "type": "text",
      "text": "|",
      "start": null,
      "end": null,
      "annotation": ""
    },
    {
      "type": "text",
      "text": "智慧",
      "start": 52.180363,
      "end": 52.860367,
      "annotation": "zhìhuì"
    },
    {
      "type": "text",
      "text": "|",
      "start": null,
      "end": null,
      "annotation": ""
    },
    {
      "type": "text",
      "text": "生物",
      "start": 52.860367,
      "end": 53.460371,
      "annotation": "shēngwù"
    },
    {
      "type": "text",
      "text": "|",
      "start": null,
      "end": null,
      "annotation": ""
    },
    {
      "type": "text",
      "text": "吗",
      "start": 53.460371,
      "end": 54.306125,
      "annotation": "ma"
    },
    {
      "type": "text",
      "text": "?\n",
      "start": null,
      "end": null,
      "annotation": ""
    },
    {
      "type": "text",
      "text": "阳奈:",
      "start": null,
      "end": 54.306125,
      "annotation": ""
    },
    {
      "type": "text",
      "text": " ",
      "start": null,
      "end": null,
      "annotation": ""
    },
    {
      "type": "text",
      "text": "啊",
      "start": 54.306125,
      "end": 55.285716,
      "annotation": "Á"
    },
    {
      "type": "text",
      "text": "? ",
      "start": null,
      "end": null,
      "annotation": ""
    },
    {
      "type": "text",
      "text": "嗯",
      "start": 55.285716,
      "end": 57.044397,
      "annotation": "Ng"
    },
    {
      "type": "text",
      "text": "...... ",
      "start": null,
      "end": null,
      "annotation": ""
    },
    {
      "type": "text",
      "text": "勉强",
      "start": 57.044397,
      "end": 58.220405,
      "annotation": "miǎnqiǎng"
    },
    {
      "type": "text",
      "text": "|",
      "start": null,
      "end": null,
      "annotation": ""
    },
    {
      "type": "text",
      "text": "算吧",
      "start": 58.220405,
      "end": 59.488583,
      "annotation": "suàn ba"
    },
    {
      "type": "text",
      "text": ",\n",
      "start": null,
      "end": null,
      "annotation": ""
    },
    {
      "type": "spacer",
      "text": "阳奈:",
      "start": null,
      "end": null,
      "annotation": ""
    },
    {
      "type": "text",
      "text": " ",
      "start": null,
      "end": null,
      "annotation": ""
    },
    {
      "type": "text",
      "text": "就是",
      "start": 59.488583,
      "end": 59.947083,
      "annotation": "jiùshì"
    },
    {
      "type": "text",
      "text": "|",
      "start": null,
      "end": null,
      "annotation": ""
    },
    {
      "type": "text",
      "text": "数学",
      "start": 59.947083,
      "end": 60.547087,
      "annotation": "shùxué"
    },
    {
      "type": "text",
      "text": "|",
      "start": null,
      "end": null,
      "annotation": ""
    },
    {
      "type": "text",
      "text": "不太好",
      "start": 60.547087,
      "end": 61.944428,
      "annotation": "bú tài hǎo"
    },
    {
      "type": "text",
      "text": ".\n",
      "start": null,
      "end": null,
      "annotation": ""
    },
    {
      "type": "text",
      "text": "蛇族船长:",
      "start": null,
      "end": null,
      "annotation": ""
    },
    {
      "type": "text",
      "text": " ",
      "start": null,
      "end": null,
      "annotation": ""
    },
    {
      "type": "text",
      "text": "嗯",
      "start": 61.944428,
      "end": 63.915016,
      "annotation": "Ng"
    },
    {
      "type": "text",
      "text": ". ",
      "start": null,
      "end": null,
      "annotation": ""
    },
    {
      "type": "text",
      "text": "先把",
      "start": 63.915016,
      "end": 64.667115,
      "annotation": "Xiān bǎ"
    },
    {
      "type": "text",
      "text": "|",
      "start": null,
      "end": null,
      "annotation": ""
    },
    {
      "type": "text",
      "text": "她",
      "start": 64.667115,
      "end": 65.360454,
      "annotation": "tā"
    },
    {
      "type": "text",
      "text": "|",
      "start": null,
      "end": null,
      "annotation": ""
    },
    {
      "type": "text",
      "text": "关到",
      "start": 65.360454,
      "end": 66.237102,
      "annotation": "guāndào"
    },
    {
      "type": "text",
      "text": "|",
      "start": null,
      "end": null,
      "annotation": ""
    },
    {
      "type": "text",
      "text": "船舱",
      "start": 66.237102,
      "end": 68.325807,
      "annotation": "chuáncāng"
    },
    {
      "type": "text",
      "text": ".\n",
      "start": null,
      "end": null,
      "annotation": ""
    },
    {
      "type": "text",
      "text": "蛇族兵AB:",
      "start": null,
      "end": null,
      "annotation": ""
    },
    {
      "type": "text",
      "text": " ",
      "start": null,
      "end": null,
      "annotation": ""
    },
    {
      "type": "text",
      "text": "是",
      "start": 68.325807,
      "end": 70.132256,
      "annotation": "Shì"
    },
    {
      "type": "text",
      "text": "!\n",
      "start": null,
      "end": null,
      "annotation": ""
    },
    {
      "type": "text",
      "text": "阳奈:",
      "start": null,
      "end": null,
      "annotation": ""
    },
    {
      "type": "text",
      "text": " ",
      "start": null,
      "end": null,
      "annotation": ""
    },
    {
      "type": "text",
      "text": "你们要",
      "start": 70.132256,
      "end": 70.807008,
      "annotation": "Nǐmen yào"
    },
    {
      "type": "text",
      "text": "|",
      "start": null,
      "end": null,
      "annotation": ""
    },
    {
      "type": "text",
      "text": "干什么",
      "start": 70.807008,
      "end": 71.641568,
      "annotation": "gàn shénme"
    },
    {
      "type": "text",
      "text": "?! ",
      "start": null,
      "end": null,
      "annotation": ""
    },
    {
      "type": "text",
      "text": "我要",
      "start": 71.641568,
      "end": 72.27705,
      "annotation": "Wǒ yào"
    },
    {
      "type": "text",
      "text": "|",
      "start": null,
      "end": null,
      "annotation": ""
    },
    {
      "type": "text",
      "text": "去",
      "start": 72.27705,
      "end": 72.487056,
      "annotation": "qù"
    },
    {
      "type": "text",
      "text": "|",
      "start": null,
      "end": null,
      "annotation": ""
    },
    {
      "type": "text",
      "text": "学校啊",
      "start": 72.487056,
      "end": 74.281941,
      "annotation": "xuéxiào a"
    },
    {
      "type": "text",
      "text": "!!",
      "start": null,
      "end": null,
      "annotation": ""
    }
  ]
}